Metadata-Version: 1.1
Name: slimmyorm
Version: 0.0.73
Summary: Lightweight wrapper for mysql.connector
Home-page: https://github.com/eddie-knight/slimmyorm
Author: Eddie Knight
Author-email: UNKNOWN
License: UNKNOWN
Platform: UNKNOWN
Classifier: Development Status :: 3 - Alpha
Classifier: Programming Language :: Python :: 3
Classifier: License :: OSI Approved :: MIT License
Classifier: Operating System :: OS Independent
